melvin/README.md
melvin/__init__.py
melvin/agents.py
melvin/bot.py
melvin/chart_agent.py
melvin/cli.py
melvin/constants.py
melvin/diagnostics_agent.py
melvin/feature_builder_ui.py
melvin/lib.py
melvin/prompts.py
melvin/tecton_utils.py
melvin/tools.py
melvin/ui.py
melvin/utils.py
melvin/data/examples.parquet
melvin/data/gotchas.md
melvin/data/sample_questions.md
melvin/data/sys_prompt.md
melvin/editors/feature_view_editor_agent.py
melvin/editors/feature_view_editor_ui.py
melvin/imgs/melvin.png
melvin/imgs/tecton.png
melvin/notebooks/extract_pydantic_models.ipynb
melvin/notebooks/generate_examples_parquet.ipynb
melvin/tecton_gen_ai/__init__.py
melvin/tecton_gen_ai/_version.py
melvin/tecton_gen_ai/api.py
melvin/tecton_gen_ai/constants.py
melvin/tecton_gen_ai/realtime_utils.py
melvin/tecton_gen_ai/agent/__init__.py
melvin/tecton_gen_ai/agent/_tool_wrappers.py
melvin/tecton_gen_ai/agent/base.py
melvin/tecton_gen_ai/agent/client.py
melvin/tecton_gen_ai/agent/service.py
melvin/tecton_gen_ai/factories/__init__.py
melvin/tecton_gen_ai/factories/llm.py
melvin/tecton_gen_ai/factories/vector_db.py
melvin/tecton_gen_ai/integrations/__init__.py
melvin/tecton_gen_ai/integrations/instructor.py
melvin/tecton_gen_ai/integrations/lancedb.py
melvin/tecton_gen_ai/integrations/langchain.py
melvin/tecton_gen_ai/integrations/llama_index.py
melvin/tecton_gen_ai/resources/feature-tool.png
melvin/tecton_gen_ai/resources/input.png
melvin/tecton_gen_ai/resources/knowledge-tool.png
melvin/tecton_gen_ai/resources/knowledge.png
melvin/tecton_gen_ai/resources/llm.png
melvin/tecton_gen_ai/resources/prompt-enriched.png
melvin/tecton_gen_ai/resources/prompt.png
melvin/tecton_gen_ai/resources/table-orig.png
melvin/tecton_gen_ai/resources/table.png
melvin/tecton_gen_ai/resources/tool.png
melvin/tecton_gen_ai/resources/vdb.png
melvin/tecton_gen_ai/tecton_utils/__init__.py
melvin/tecton_gen_ai/tecton_utils/_internal.py
melvin/tecton_gen_ai/tecton_utils/_schema_utils.py
melvin-0.1.3.dist-info/METADATA
melvin-0.1.3.dist-info/WHEEL
melvin-0.1.3.dist-info/entry_points.txt
melvin-0.1.3.dist-info/RECORD
