Metadata-Version: 2.4
Name: melvin
Version: 0.1.3
Summary: [private preview] Tecton Melvin
Project-URL: Homepage, https://tecton.ai
Project-URL: Documentation, https://docs.tecton.ai
Author-email: "Tecton, Inc." <support@tecton.ai>
License: Tecton Proprietary
Classifier: License :: Other/Proprietary License
Classifier: Operating System :: OS Independent
Classifier: Programming Language :: Python :: 3
Requires-Python: >=3.9
Requires-Dist: black>=24.1.0
Requires-Dist: cloudpickle>=2.0.0
Requires-Dist: diskcache>=5.6.3
Requires-Dist: ipywidgets>=8.1.5
Requires-Dist: lancedb==0.18.0
Requires-Dist: langchain-community>=0.3.0
Requires-Dist: langchain-core>0.3
Requires-Dist: langchain-openai>=0.1.23
Requires-Dist: langchain>=0.3
Requires-Dist: llama-index>=0.1.0
Requires-Dist: logfire>=0.1.1
Requires-Dist: matplotlib>=3.8.0
Requires-Dist: openai>=1.1.0
Requires-Dist: pandas>=2.2.1
Requires-Dist: plotly>=5.22.0
Requires-Dist: snowflake-connector-python>=3.11.0
Requires-Dist: streamlit-flow-component>=0.0.1
Requires-Dist: streamlit>=1.43.0
Requires-Dist: tecton-client>=0.3.0
Requires-Dist: tecton-runtime==1.1.5
Requires-Dist: tecton==1.1.5
Requires-Dist: tecton[rift]==1.1.5
Requires-Dist: typing-extensions>=4.5
Requires-Dist: watchdog>=0.10.0
